Metadata-Version: 2.1
Name: django-tenant-admin
Version: 0.1.0
Home-page: https://gitlab.com/os4d/django-tenant-admin
Download-URL: https://gitlab.com/os4d/django-tenant-admin
Author: os4d
Author-email: dev@os4d.org
License: MIT
Platform: any
Classifier: Environment :: Web Environment
Classifier: Framework :: Django
Classifier: Operating System :: OS Independent
Classifier: Framework :: Django :: 3.2
Classifier: Framework :: Django :: 4.0
Classifier: Framework :: Django :: 4.1
Classifier: Programming Language :: Python :: 3.9
Classifier: Programming Language :: Python :: 3.10
Classifier: Intended Audience :: Developers
Provides-Extra: test
Provides-Extra: dev
Provides-Extra: docs
License-File: LICENSE
